magento_config_tool/__init__.py
magento_config_tool/magento_config_tool.py
magento_config_tool-1.0.7.dist-info/METADATA
magento_config_tool-1.0.7.dist-info/WHEEL
magento_config_tool-1.0.7.dist-info/entry_points.txt
magento_config_tool-1.0.7.dist-info/top_level.txt
magento_config_tool-1.0.7.dist-info/RECORD
