Metadata-Version: 2.2
Name: magento-config-tool
Version: 1.0.7
Summary: A terminal-based Magento configuration management tool
Home-page: https://github.com/genaker/magento-config-tool
Author: Yehor Shytikov
Author-email: yegorshytikov@email.com
Classifier: Programming Language :: Python :: 3
Classifier: License :: OSI Approved :: MIT License
Classifier: Operating System :: POSIX :: Linux
Classifier: Operating System :: MacOS
Classifier: Environment :: Console
Requires-Python: >=3.6
Requires-Dist: tabulate
Requires-Dist: sqlalchemy
Requires-Dist: mysql-connector-python
Dynamic: author
Dynamic: author-email
Dynamic: classifier
Dynamic: description
Dynamic: description-content-type
Dynamic: home-page
Dynamic: requires-dist
Dynamic: requires-python
Dynamic: summary
